dokku_py/__init__.py
dokku_py-0.1.0.dist-info/LICENSE
dokku_py-0.1.0.dist-info/METADATA
dokku_py-0.1.0.dist-info/WHEEL
dokku_py-0.1.0.dist-info/entry_points.txt
dokku_py-0.1.0.dist-info/RECORD
