Metadata-Version: 2.1
Name: dokku-py
Version: 0.1.0
Summary: Python version of the Dokku CLI
Home-page: https://github.com/search5/dokku-py
License: BSD-3-Clause
Keywords: dokku
Author: lee ji-ho
Author-email: search5@gmail.com
Requires-Python: >=3.10,<4.0
Classifier: Development Status :: 4 - Beta
Classifier: License :: OSI Approved :: BSD License
Classifier: Operating System :: OS Independent
Classifier: Programming Language :: Python :: 3
Classifier: Programming Language :: Python :: 3.10
Classifier: Programming Language :: Python :: 3.11
Classifier: Programming Language :: Python :: 3.12
Classifier: Programming Language :: Python :: 3.13
Classifier: Topic :: Software Development
Classifier: Topic :: Software Development :: Libraries
Classifier: Topic :: System :: System Shells
Classifier: Topic :: Utilities
Project-URL: Repository, https://github.com/search5/dokku-py
